equal_logger/__init__.py
equal_logger/logger.py
equal_logger/sql_quality_test.py
equal_logger/integrations/__init__.py
equal_logger/integrations/azure_integration.py
equal_logger/integrations/gcp_integration.py
equal_logger-2.0.0.dist-info/licenses/LICENSE
equal_logger-2.0.0.dist-info/METADATA
equal_logger-2.0.0.dist-info/WHEEL
equal_logger-2.0.0.dist-info/top_level.txt
equal_logger-2.0.0.dist-info/RECORD
